constelation_astronomer/__init__.py
constelation_astronomer/astronomer.py
test/__init__.py
test/test_function.py
constelation_astronomer-1.1.4.dist-info/LICENSE
constelation_astronomer-1.1.4.dist-info/METADATA
constelation_astronomer-1.1.4.dist-info/WHEEL
constelation_astronomer-1.1.4.dist-info/top_level.txt
constelation_astronomer-1.1.4.dist-info/RECORD
