Metadata-Version: 2.1
Name: constelation_astronomer
Version: 1.1.4
Summary: constelation-astronomer: results processing package for CONSTELATION coupled model
Home-page: https://github.com/warrenau/astronomer
Author: Austin Warren
Author-email: warrenau@oregonstate.edu
License: MIT License
Keywords: python,data processing,Serpent 2,STAR-CCM+
Classifier: Development Status :: 4 - Beta
Classifier: Intended Audience :: Science/Research
Classifier: License :: OSI Approved :: MIT License
Classifier: Programming Language :: Python :: 3
Classifier: Operating System :: Microsoft :: Windows
Classifier: Operating System :: POSIX :: Linux
License-File: LICENSE
Requires-Dist: numpy
Requires-Dist: matplotlib
